{
  "name": "Vanadium Demo Pack",
  "author": "Vanadium Team",
  "description": "Structured modular SPIR-V pack with world pipelines and reusable shader libs.",
  "version": "2.0.0",
  "supportedMinecraftVersion": "1.21.1",
  "icon": "icon.png",
  "modules": {
    "vertex": {
      "path": "world-0/composite1.vert.spv",
      "entryPoint": "main"
    },
    "fragment": {
      "path": "world-0/composite1.frag.spv",
      "entryPoint": "main"
    },
    "compute": {
      "path": "lib/misc/prepare.comp.spv",
      "entryPoint": "main"
    }
  },
  "descriptorLayout": [],
  "renderPass": {
    "colorAttachments": 1,
    "depthAttachment": true
  }
}
